simple_useragent/__init__.py
simple_useragent/core.py
simple_useragent/data/fallback.json
simple_useragent-0.1.5.dist-info/LICENSE
simple_useragent-0.1.5.dist-info/METADATA
simple_useragent-0.1.5.dist-info/WHEEL
simple_useragent-0.1.5.dist-info/top_level.txt
simple_useragent-0.1.5.dist-info/RECORD
