Metadata-Version: 2.1
Name: simple-useragent
Version: 0.1.5
Summary: Seamlessly fetch authentic and current user agents with ease
Home-page: https://github.com/Lennolium/simple-useragent
Author: Lennart Haack
Author-email: info@lennolium.dev
License: GPL-3.0
Project-URL: Bug Tracker, https://github.com/Lennolium/simple-useragent/issues
Project-URL: Source, https://github.com/Lennolium/simple-useragent
Project-URL: Download, https://github.com/Lennolium/simple-useragent/releases/latest
Project-URL: Documentation, https://github.com/Lennolium/simple-useragent/README.md
Platform: any
Classifier: Development Status :: 5 - Production/Stable
Classifier: Topic :: Utilities
Classifier: Programming Language :: Python :: 3
Classifier: Programming Language :: Python :: 3.8
Classifier: Programming Language :: Python :: 3.12
Classifier: Programming Language :: Python :: 3 :: Only
Classifier: License :: OSI Approved :: GNU General Public License v3 (GPLv3)
Classifier: Operating System :: OS Independent
Classifier: Operating System :: POSIX :: Linux
Classifier: Operating System :: Unix
Classifier: Operating System :: MacOS
Classifier: Operating System :: Microsoft :: Windows
Classifier: Natural Language :: English
Classifier: Intended Audience :: Developers
Classifier: Intended Audience :: Science/Research
Requires-Python: >=3.8
License-File: LICENSE
Requires-Dist: beautifulsoup4 ==4.12.3
Requires-Dist: platformdirs ==4.2.0
Requires-Dist: requests ==2.31.0
Requires-Dist: ua-parser ==0.18.0
